tubeup/TubeUp.py
tubeup/__init__.py
tubeup/__main__.py
tubeup/utils.py
tubeup-2025.9.23.dist-info/licenses/LICENSE
tubeup-2025.9.23.dist-info/METADATA
tubeup-2025.9.23.dist-info/WHEEL
tubeup-2025.9.23.dist-info/entry_points.txt
tubeup-2025.9.23.dist-info/top_level.txt
tubeup-2025.9.23.dist-info/RECORD
