Metadata-Version: 2.4
Name: tubeup
Version: 2025.9.23
Summary: VOD service to Archive.org uploader
Author: Bibliotheca Anonoma
License-Expression: GPL-3.0-or-later
Project-URL: homepage, https://github.com/bibanon/tubeup
Project-URL: source, https://github.com/bibanon/tubeup.git
Project-URL: issues, https://github.com/bibanon/tubeup/issues
Keywords: archive.org,archiving,bibliotheca anonoma,internet archive,vod,video,youtube,youtube-dl,youtube-dlc,yt-dlp
Classifier: Development Status :: 5 - Production/Stable
Classifier: Environment :: Console
Classifier: Intended Audience :: End Users/Desktop
Classifier: Operating System :: POSIX :: Linux
Classifier: Programming Language :: Python :: 3 :: Only
Classifier: Programming Language :: Python :: 3.9
Classifier: Programming Language :: Python :: 3.10
Classifier: Programming Language :: Python :: 3.11
Classifier: Programming Language :: Python :: 3.12
Classifier: Programming Language :: Python :: 3.13
Classifier: Programming Language :: Python :: Implementation
Classifier: Programming Language :: Python :: Implementation :: CPython
Classifier: Programming Language :: Python :: Implementation :: PyPy
Classifier: Topic :: Multimedia :: Video
Classifier: Topic :: Utilities
Requires-Python: >=3.9
License-File: LICENSE
Requires-Dist: internetarchive
Requires-Dist: docopt==0.6.2
Requires-Dist: yt-dlp[curl-cffi,default]
Dynamic: license-file
